chronostore/__init__.py
chronostore/engine.py
chronostore/schema.py
chronostore-0.1.0.dist-info/licenses/LICENSE
chronostore-0.1.0.dist-info/METADATA
chronostore-0.1.0.dist-info/WHEEL
chronostore-0.1.0.dist-info/top_level.txt
chronostore-0.1.0.dist-info/RECORD
