Metadata-Version: 2.4
Name: chronostore
Version: 0.1.0
Summary: The simplest binary time series store. No DB. No Server. Just mmap. Built for append-only local data.
Author-email: Mickael Burguet <your.email@example.com>
License: MIT License
Project-URL: Homepage, https://github.com/rundef/chronostore
Project-URL: Repository, https://github.com/rundef/chronostore
Project-URL: Issues, https://github.com/rundef/chronostore/issues
Classifier: Programming Language :: Python :: 3
Classifier: Programming Language :: Python :: 3.10
Classifier: Programming Language :: Python :: 3.11
Classifier: Programming Language :: Python :: 3.12
Classifier: Programming Language :: Python :: 3.13
Classifier: License :: OSI Approved :: MIT License
Classifier: Operating System :: OS Independent
Classifier: Intended Audience :: Developers
Classifier: Topic :: Software Development :: Libraries
Classifier: Topic :: System :: Filesystems
Classifier: Topic :: Scientific/Engineering :: Information Analysis
Requires-Python: >=3.10
License-File: LICENSE
Requires-Dist: numpy>=1.24.0
Requires-Dist: pandas>=1.4.0
Requires-Dist: lmdb>=1.4.1
Requires-Dist: pattern_kit>=2.0.0
Dynamic: license-file
